[
  {
    "id": "diagnosis_funkcionalnaja_dispespija",
    "type": "diagnosis",
    "label": "Диспепсия функциональная",
    "icd_code": "K30.0"
  },
  {
    "id": "diagnosis_sindrom_razdrazhennogo_kishhechnika_s_diareej",
    "type": "diagnosis",
    "label": "Синдром раздраженного кишечника с диареей",
    "icd_code": "K58.0"
  },
  {
    "id": "diagnosis_sindrom_razdrazhennogo_kishhechnika_bez_diareji",
    "type": "diagnosis",
    "label": "Синдром раздраженного кишечника без диареи",
    "icd_code": "K58.9"
  },
  {
    "id": "symptom_bol_v_epigastrii",
    "type": "symptom",
    "label": "Боль в эпигастрии"
  },
  {
    "id": "symptom_zhzhenie_v_epigastrii",
    "type": "symptom",
    "label": "Жжение в эпигастрии"
  },
  {
    "id": "symptom_chuvstvo_perepolnenija_v_epigastrii",
    "type": "symptom",
    "label": "Чувство переполнения в эпигастрии"
  },
  {
    "id": "symptom_rannee_nasychenie",
    "type": "symptom",
    "label": "Раннее насыщение"
  },
  {
    "id": "symptom_diareja",
    "type": "symptom",
    "label": "Диарея"
  },
  {
    "id": "symptom_zapor",
    "type": "symptom",
    "label": "Запор"
  },
  {
    "id": "symptom_abdominalnaja_bol",
    "type": "symptom",
    "label": "Абдоминальная боль"
  },
  {
    "id": "symptom_izmenenie_chastoty_stula",
    "type": "symptom",
    "label": "Изменение частоты стула"
  },
  {
    "id": "symptom_izmenenie_formy_stula",
    "type": "symptom",
    "label": "Изменение формы стула"
  },
  {
    "id": "symptom_metorizm",
    "type": "symptom",
    "label": "Метеоризм"
  },
  {
    "id": "symptom_vzdutije_zhivota",
    "type": "symptom",
    "label": "Вздутие живота"
  },
  {
    "id": "symptom_toshnota",
    "type": "symptom",
    "label": "Тошнота"
  },
  {
    "id": "symptom_rvota",
    "type": "symptom",
    "label": "Рвота"
  },
  {
    "id": "symptom_otryzhka",
    "type": "symptom",
    "label": "Отрыжка"
  },
  {
    "id": "symptom_reflyuks_efagita",
    "type": "symptom",
    "label": "Рефлюкс-эзофагит"
  },
  {
    "id": "symptom_diskomfort_zhk",
    "type": "symptom",
    "label": "Дискомфорт желудочно-кишечный"
  },
  {
    "id": "symptom_bol_posle_edy",
    "type": "symptom",
    "label": "Боль после еды"
  },
  {
    "id": "symptom_bol_umenshaetsja_posle_defekacii",
    "type": "symptom",
    "label": "Боль уменьшается после дефекации"
  },
  {
    "id": "symptom_gazoobrazovanie",
    "type": "symptom",
    "label": "Газообразование"
  },
  {
    "id": "symptom_bol_v_nizhnem_levom_kvadrante",
    "type": "symptom",
    "label": "Боль в нижнем левом квадранте"
  },
  {
    "id": "symptom_bol_v_grudnoj_kletke",
    "type": "symptom",
    "label": "Боль в грудной клетке"
  },
  {
    "id": "symptom_trevozhnost",
    "type": "symptom",
    "label": "Тревожность"
  },
  {
    "id": "sign_oblozhennost_jazyka",
    "type": "symptom",
    "label": "Обложенность языка"
  },
  {
    "id": "sign_bolезненnost_pri_palpatsii_epigastrii",
    "type": "symptom",
    "label": "Болезненность при пальпации в эпигастрии"
  },
  {
    "id": "symptom_gipergidroz_ladoni_i_stop",
    "type": "symptom",
    "label": "Гипергидроз ладони и стоп"
  },
  {
    "id": "symptom_stojkij_krasnyj_dermografizm",
    "type": "symptom",
    "label": "Стойкий красный дермографизм"
  },
  {
    "id": "symptom_arterialnaja_gipotenzija",
    "type": "symptom",
    "label": "Артериальная гипотензия"
  },
  {
    "id": "sign_lihorodka",
    "type": "symptom",
    "label": "Лихорадка"
  },
  {
    "id": "sign_gepatomegaliya",
    "type": "symptom",
    "label": "Гепатомегалия"
  },
  {
    "id": "sign_splenomegaliya",
    "type": "symptom",
    "label": "Спленомегалия"
  },
  {
    "id": "sign_anemiya",
    "type": "symptom",
    "label": "Анемия"
  },
  {
    "id": "sign_leukocitoz",
    "type": "symptom",
    "label": "Лейкоцитоз"
  },
  {
    "id": "sign_skrytaia_krov_v_kale",
    "type": "symptom",
    "label": "Скрытая кровь в кале"
  },
  {
    "id": "sign_steatoreja",
    "type": "symptom",
    "label": "Стеаторея"
  },
  {
    "id": "sign_polifekaliia",
    "type": "symptom",
    "label": "Полифекалия"
  },
  {
    "id": "symptom_poterja_vesa",
    "type": "symptom",
    "label": "Необъяснимая потеря веса"
  },
  {
    "id": "symptom_melena",
    "type": "symptom",
    "label": "Мелена"
  },
  {
    "id": "symptom_gemetemezis",
    "type": "symptom",
    "label": "Гематемезис"
  },
  {
    "id": "symptom_disfagia",
    "type": "symptom",
    "label": "Дисфагия"
  }
]