[
  {
    "source": "symptom_upper_abdominal_pain",
    "target": "diagnosis_chronic_pancreatitis_children",
    "type": "supports",
    "weight": 0.95,
    "evidence": "характерный и постоянный симптом ХП – боль в верхнем отделе живота",
    "properties": {}
  },
  {
    "source": "symptom_epigastric_pain",
    "target": "diagnosis_chronic_pancreatitis_children",
    "type": "supports",
    "weight": 0.95,
    "evidence": "эпигастральные ... боли",
    "properties": {}
  },
  {
    "source": "symptom_belt_like_pain",
    "target": "diagnosis_chronic_pancreatitis_children",
    "type": "supports",
    "weight": 0.95,
    "evidence": "опоясывающие боли",
    "properties": {}
  },
  {
    "source": "symptom_radiating_back",
    "target": "diagnosis_chronic_pancreatitis_children",
    "type": "supports",
    "weight": 0.95,
    "evidence": "иррадиирующие в спину",
    "properties": {}
  },
  {
    "source": "symptom_radiating_left_arm",
    "target": "diagnosis_chronic_pancreatitis_children",
    "type": "supports",
    "weight": 0.95,
    "evidence": "иррадиирующие в левую руку",
    "properties": {}
  },
  {
    "source": "symptom_radiating_left_side",
    "target": "diagnosis_chronic_pancreatitis_children",
    "type": "supports",
    "weight": 0.95,
    "evidence": "иррадиирующие в левый бок",
    "properties": {}
  },
  {
    "source": "symptom_pain_post_meal",
    "target": "diagnosis_chronic_pancreatitis_children",
    "type": "supports",
    "weight": 0.95,
    "evidence": "усиливается после приёма пищи",
    "properties": {}
  },
  {
    "source": "symptom_pain_physical_exertion",
    "target": "diagnosis_chronic_pancreatitis_children",
    "type": "supports",
    "weight": 0.95,
    "evidence": "усиливается ... физической нагрузки",
    "properties": {}
  },
  {
    "source": "symptom_dull_pain",
    "target": "diagnosis_chronic_pancreatitis_children",
    "type": "supports",
    "weight": 0.75,
    "evidence": "Боли могут быть тупые",
    "properties": {}
  },
  {
    "source": "symptom_aching_pain",
    "target": "diagnosis_chronic_pancreatitis_children",
    "type": "supports",
    "weight": 0.75,
    "evidence": "ноющие",
    "properties": {}
  },
  {
    "source": "symptom_stabbing_pain",
    "target": "diagnosis_chronic_pancreatitis_children",
    "type": "supports",
    "weight": 0.75,
    "evidence": "колющие",
    "properties": {}
  },
  {
    "source": "symptom_paroxysmal_pain",
    "target": "diagnosis_chronic_pancreatitis_children",
    "type": "supports",
    "weight": 0.75,
    "evidence": "приступообразные",
    "properties": {}
  },
  {
    "source": "symptom_persistent_pain",
    "target": "diagnosis_chronic_pancreatitis_children",
    "type": "supports",
    "weight": 0.75,
    "evidence": "упорные",
    "properties": {}
  },
  {
    "source": "symptom_dry_mouth",
    "target": "diagnosis_chronic_pancreatitis_children",
    "type": "supports",
    "weight": 0.75,
    "evidence": "Сухость во рту",
    "properties": {}
  },
  {
    "source": "symptom_increased_salivation",
    "target": "diagnosis_chronic_pancreatitis_children",
    "type": "supports",
    "weight": 0.75,
    "evidence": "повышенное слюноотделение",
    "properties": {}
  },
  {
    "source": "symptom_nausea",
    "target": "diagnosis_chronic_pancreatitis_children",
    "type": "supports",
    "weight": 0.75,
    "evidence": "тошнота",
    "properties": {}
  },
  {
    "source": "symptom_vomiting",
    "target": "diagnosis_chronic_pancreatitis_children",
    "type": "supports",
    "weight": 0.75,
    "evidence": "рвота",
    "properties": {}
  },
  {
    "source": "symptom_loss_of_appetite",
    "target": "diagnosis_chronic_pancreatitis_children",
    "type": "supports",
    "weight": 0.75,
    "evidence": "нарушение аппетита",
    "properties": {}
  },
  {
    "source": "symptom_flatulence",
    "target": "diagnosis_chronic_pancreatitis_children",
    "type": "supports",
    "weight": 0.75,
    "evidence": "метеоризм",
    "properties": {}
  },
  {
    "source": "symptom_fatty_gray_stool",
    "target": "diagnosis_chronic_pancreatitis_children",
    "type": "supports",
    "weight": 0.75,
    "evidence": "кашицеобразный стул серого цвета с жирным блеском",
    "properties": {}
  },
  {
    "source": "symptom_polyfecalia",
    "target": "diagnosis_chronic_pancreatitis_children",
    "type": "supports",
    "weight": 0.75,
    "evidence": "полифекалия",
    "properties": {}
  },
  {
    "source": "symptom_weight_loss",
    "target": "diagnosis_chronic_pancreatitis_children",
    "type": "supports",
    "weight": 0.75,
    "evidence": "Снижение массы тела – у детей частый симптом",
    "properties": {}
  },
  {
    "source": "symptom_vitamin_k_deficiency",
    "target": "diagnosis_chronic_pancreatitis_children",
    "type": "supports",
    "weight": 0.25,
    "evidence": "подкожные кровоизлияния (недостаток вит К)",
    "properties": {}
  },
  {
    "source": "symptom_vitamin_d_deficiency",
    "target": "diagnosis_chronic_pancreatitis_children",
    "type": "supports",
    "weight": 0.25,
    "evidence": "боли в костях (недостаток вит Д)",
    "properties": {}
  },
  {
    "source": "symptom_vitamin_a_deficiency",
    "target": "diagnosis_chronic_pancreatitis_children",
    "type": "supports",
    "weight": 0.25,
    "evidence": "гемералопия (недостаток вит А)",
    "properties": {}
  },
  {
    "source": "symptom_pancreatogenic_diabetes",
    "target": "diagnosis_chronic_pancreatitis_children",
    "type": "supports",
    "weight": 0.5,
    "evidence": "Симптомы сахарного диабета ... наблюдаются при развитии эндокринной недостаточности ПЖ",
    "properties": {}
  },
  {
    "source": "symptom_thirst",
    "target": "diagnosis_chronic_pancreatitis_children",
    "type": "supports",
    "weight": 0.5,
    "evidence": "жажда ... наблюдаются при развитии эндокринной недостаточности ПЖ",
    "properties": {}
  },
  {
    "source": "symptom_polyuria",
    "target": "diagnosis_chronic_pancreatitis_children",
    "type": "supports",
    "weight": 0.5,
    "evidence": "полиурия ... наблюдаются при развитии эндокринной недостаточности ПЖ",
    "properties": {}
  },
  {
    "source": "symptom_emotional_lability",
    "target": "diagnosis_chronic_pancreatitis_children",
    "type": "supports",
    "weight": 0.75,
    "evidence": "Эмоциональная лабильность",
    "properties": {}
  },
  {
    "source": "symptom_irritability",
    "target": "diagnosis_chronic_pancreatitis_children",
    "type": "supports",
    "weight": 0.75,
    "evidence": "раздражительность",
    "properties": {}
  },
  {
    "source": "symptom_headache",
    "target": "diagnosis_chronic_pancreatitis_children",
    "type": "supports",
    "weight": 0.75,
    "evidence": "головная боль",
    "properties": {}
  },
  {
    "source": "symptom_weakness",
    "target": "diagnosis_chronic_pancreatitis_children",
    "type": "supports",
    "weight": 0.75,
    "evidence": "слабость",
    "properties": {}
  },
  {
    "source": "symptom_pale_skin",
    "target": "diagnosis_chronic_pancreatitis_children",
    "type": "supports",
    "weight": 0.75,
    "evidence": "серовато‑зеленоватый бледный оттенок кожи",
    "properties": {}
  },
  {
    "source": "symptom_cyanosis_under_eyes",
    "target": "diagnosis_chronic_pancreatitis_children",
    "type": "supports",
    "weight": 0.75,
    "evidence": "тени или синева под глазами",
    "properties": {}
  },
  {
    "source": "symptom_dry_lips",
    "target": "diagnosis_chronic_pancreatitis_children",
    "type": "supports",
    "weight": 0.75,
    "evidence": "сухость губ",
    "properties": {}
  },
  {
    "source": "symptom_cracks_in_mouth",
    "target": "diagnosis_chronic_pancreatitis_children",
    "type": "supports",
    "weight": 0.75,
    "evidence": "заеды",
    "properties": {}
  },
  {
    "source": "symptom_shofar_zone_pain",
    "target": "diagnosis_chronic_pancreatitis_children",
    "type": "supports",
    "weight": 0.5,
    "evidence": "болезненность в зоне Шофарра",
    "properties": {}
  },
  {
    "source": "symptom_meier_robertson_point_pain",
    "target": "diagnosis_chronic_pancreatitis_children",
    "type": "supports",
    "weight": 0.5,
    "evidence": "болезненность в точке Мейо‑Робсона",
    "properties": {}
  },
  {
    "source": "symptom_kacha_point_pain",
    "target": "diagnosis_chronic_pancreatitis_children",
    "type": "supports",
    "weight": 0.5,
    "evidence": "болезненность в точке Кача",
    "properties": {}
  },
  {
    "source": "symptom_de_jarden_point_pain",
    "target": "diagnosis_chronic_pancreatitis_children",
    "type": "supports",
    "weight": 0.5,
    "evidence": "болезненность в точке Де‑Жардена",
    "properties": {}
  },
  {
    "source": "symptom_grotta_sign",
    "target": "diagnosis_chronic_pancreatitis_children",
    "type": "supports",
    "weight": 0.5,
    "evidence": "симптом Гротта",
    "properties": {}
  },
  {
    "source": "symptom_bergmann_kalka_sign",
    "target": "diagnosis_chronic_pancreatitis_children",
    "type": "supports",
    "weight": 0.5,
    "evidence": "симптом Бергмана‑Калька",
    "properties": {}
  },
  {
    "source": "symptom_voskresensky_sign",
    "target": "diagnosis_chronic_pancreatitis_children",
    "type": "supports",
    "weight": 0.5,
    "evidence": "симптом Воскресенского",
    "properties": {}
  },
  {
    "source": "symptom_kacha_sign",
    "target": "diagnosis_chronic_pancreatitis_children",
    "type": "supports",
    "weight": 0.5,
    "evidence": "симптом Кача",
    "properties": {}
  },
  {
    "source": "symptom_georgievsky_mussee_sign",
    "target": "diagnosis_chronic_pancreatitis_children",
    "type": "supports",
    "weight": 0.5,
    "evidence": "симптом Георгиевского‑Мюсси",
    "properties": {}
  },
  {
    "source": "symptom_nausea",
    "target": "symptom_vomiting",
    "type": "co-occurs",
    "weight": 0.75,
    "evidence": "Диспепсические расстройства: тошнота; рвота;",
    "properties": {}
  },
  {
    "source": "symptom_flatulence",
    "target": "symptom_fatty_gray_stool",
    "type": "co-occurs",
    "weight": 0.75,
    "evidence": "метеоризм; кашицеобразный стул серого цвета с жирным блеском",
    "properties": {}
  },
  {
    "source": "symptom_weight_loss",
    "target": "symptom_fatty_gray_stool",
    "type": "co-occurs",
    "weight": 0.75,
    "evidence": "Снижение массы тела ... При прогрессировании внешнесекреторной недостаточности появляются полифекалия и стул с жирным блеском.",
    "properties": {}
  }
]