{
  "protocol_id": "p_98de2ffb83",
  "nodes": [
    {
      "id": "diagnosis_acute_mesenteric_ischemia",
      "type": "diagnosis",
      "label": "Острая мезентериальная ишемия",
      "icd_code": "K55.0"
    },
    {
      "id": "symptom_vnezapnaya_intensivnaya_abdominalnaya_bol",
      "type": "symptom",
      "label": "Внезапная интенсивная абдоминальная боль"
    },
    {
      "id": "symptom_spontannoe_oporozhnenie_kishechnika_rvota",
      "type": "symptom",
      "label": "Спонтанное опорожнение кишечника (рвота)"
    },
    {
      "id": "symptom_spontannoe_oporozhnenie_kishechnika_diareya",
      "type": "symptom",
      "label": "Спонтанное опорожнение кишечника (диарея)"
    },
    {
      "id": "symptom_primes_krovi_v_rvote",
      "type": "symptom",
      "label": "Примесь крови в рвоте"
    },
    {
      "id": "symptom_primes_krovi_v_stule",
      "type": "symptom",
      "label": "Примесь крови в стуле"
    },
    {
      "id": "symptom_simptom_blinova",
      "type": "symptom",
      "label": "Симптом Блинова (повышение АД при окклюзии верхней брыжеечной артерии)"
    },
    {
      "id": "symptom_bradykardia",
      "type": "symptom",
      "label": "Брадикардия"
    },
    {
      "id": "symptom_myagkiy_zhivot",
      "type": "symptom",
      "label": "Мягкий живот"
    },
    {
      "id": "symptom_vzdutiy_zhivot",
      "type": "symptom",
      "label": "Вздутый живот"
    },
    {
      "id": "symptom_boleznennyy_zhivot",
      "type": "symptom",
      "label": "Болезненный живот"
    },
    {
      "id": "symptom_shchetkin_blyumberga",
      "type": "symptom",
      "label": "Симптом Щеткина‑Блюмберга"
    },
    {
      "id": "symptom_tahikardia",
      "type": "symptom",
      "label": "Тахикардия"
    },
    {
      "id": "symptom_leykotsitoz",
      "type": "symptom",
      "label": "Лейкоцитоз (>12 ×10⁹/л) или лейкопения (<4 ×10⁹/л)"
    },
    {
      "id": "symptom_febrile_or_hypothermia",
      "type": "symptom",
      "label": "Температура тела >38 °C или <36 °C"
    },
    {
      "id": "symptom_gipotenzia",
      "type": "symptom",
      "label": "Гипотензия (АД <90 мм рт. ст.)"
    },
    {
      "id": "symptom_gipotrofuzia",
      "type": "symptom",
      "label": "Гипоперфузия (олигоурия, лактацидоз)"
    },
    {
      "id": "symptom_abdominalnyy_sepsis",
      "type": "symptom",
      "label": "Абдоминальный сепсис"
    },
    {
      "id": "symptom_sirs",
      "type": "symptom",
      "label": "Системный воспалительный ответ (SIRS)"
    },
    {
      "id": "symptom_polyorganaya_nedostatochnost",
      "type": "symptom",
      "label": "Полиорганная недостаточность"
    },
    {
      "id": "symptom_refrakternyy_septicheskiy_shok",
      "type": "symptom",
      "label": "Рефрактерный септический шок"
    },
    {
      "id": "symptom_mondora",
      "type": "symptom",
      "label": "Симптом Мондора (пальпация инфильтрата)"
    },
    {
      "id": "symptom_svobodnaya_zhidkost_v_brushnoi_polosti",
      "type": "symptom",
      "label": "Свободная жидкость в брюшной полости"
    },
    {
      "id": "symptom_vnutristennyy_gaz_v_kishe",
      "type": "symptom",
      "label": "Внутристенный газ в кишечнике"
    },
    {
      "id": "symptom_gaz_v_portalnoi_sisteme",
      "type": "symptom",
      "label": "Газ в портальной системе"
    },
    {
      "id": "symptom_pnevmatoz",
      "type": "symptom",
      "label": "Пневматоз"
    },
    {
      "id": "symptom_otek_bryzhyeiki",
      "type": "symptom",
      "label": "Отёк брыжейки"
    },
    {
      "id": "symptom_utolshenie_stenki_kishki",
      "type": "symptom",
      "label": "Утолщение стенки кишки"
    },
    {
      "id": "symptom_assit",
      "type": "symptom",
      "label": "Асцит"
    },
    {
      "id": "symptom_peritonit",
      "type": "symptom",
      "label": "Перитонит"
    },
    {
      "id": "symptom_gnoinyy_ekssudat",
      "type": "symptom",
      "label": "Гнойный экссудат"
    },
    {
      "id": "symptom_nizkaya_peristaltika",
      "type": "symptom",
      "label": "Снижение перистальтики"
    },
    {
      "id": "symptom_otсутstvie_peristaltiki",
      "type": "symptom",
      "label": "Отсутствие перистальтики"
    },
    {
      "id": "symptom_giperkoagulaciya",
      "type": "symptom",
      "label": "Гиперкоагуляция"
    },
    {
      "id": "symptom_povyshennyi_uroven_d_dimera",
      "type": "symptom",
      "label": "Повышенный уровень Д‑димеров"
    },
    {
      "id": "symptom_povyshennyi_uroven_lakata",
      "type": "symptom",
      "label": "Повышенный уровень лактата"
    }
  ],
  "edges": [
    {
      "source": "symptom_vnezapnaya_intensivnaya_abdominalnaya_bol",
      "target": "diagnosis_acute_mesenteric_ischemia",
      "type": "supports",
      "weight": 0.95,
      "evidence": "«клиническая триада»: внезапная интенсивная абдоминальная боль",
      "properties": {}
    },
    {
      "source": "symptom_spontannoe_oporozhnenie_kishechnika_rvota",
      "target": "diagnosis_acute_mesenteric_ischemia",
      "type": "supports",
      "weight": 0.95,
      "evidence": "спонтанное опорожнение кишечника (рвота",
      "properties": {}
    },
    {
      "source": "symptom_spontannoe_oporozhnenie_kishechnika_diareya",
      "target": "diagnosis_acute_mesenteric_ischemia",
      "type": "supports",
      "weight": 0.95,
      "evidence": "спонтанное опорожнение кишечника (диарея",
      "properties": {}
    },
    {
      "source": "symptom_primes_krovi_v_rvote",
      "target": "diagnosis_acute_mesenteric_ischemia",
      "type": "supports",
      "weight": 0.75,
      "evidence": "примесь крови в рвоте",
      "properties": {}
    },
    {
      "source": "symptom_primes_krovi_v_stule",
      "target": "diagnosis_acute_mesenteric_ischemia",
      "type": "supports",
      "weight": 0.75,
      "evidence": "примесь крови в стуле",
      "properties": {}
    },
    {
      "source": "symptom_bradykardia",
      "target": "diagnosis_acute_mesenteric_ischemia",
      "type": "supports",
      "weight": 0.75,
      "evidence": "брадикардия",
      "properties": {}
    },
    {
      "source": "symptom_simptom_blinova",
      "target": "diagnosis_acute_mesenteric_ischemia",
      "type": "supports",
      "weight": 0.75,
      "evidence": "симптом Блинова",
      "properties": {}
    },
    {
      "source": "symptom_shchetkin_blyumberga",
      "target": "diagnosis_acute_mesenteric_ischemia",
      "type": "supports",
      "weight": 0.75,
      "evidence": "симптом Щеткина‑Блюмберга",
      "properties": {}
    },
    {
      "source": "symptom_tahikardia",
      "target": "diagnosis_acute_mesenteric_ischemia",
      "type": "supports",
      "weight": 0.75,
      "evidence": "тахикардия",
      "properties": {}
    },
    {
      "source": "symptom_leykotsitoz",
      "target": "diagnosis_acute_mesenteric_ischemia",
      "type": "supports",
      "weight": 0.75,
      "evidence": "лейкоцитоз (>12 ×10⁹/л) или лейкопения (<4 ×10⁹/л)",
      "properties": {}
    },
    {
      "source": "symptom_febrile_or_hypothermia",
      "target": "diagnosis_acute_mesenteric_ischemia",
      "type": "supports",
      "weight": 0.75,
      "evidence": "температура тела >38 °C или <36 °C",
      "properties": {}
    },
    {
      "source": "symptom_gipotenzia",
      "target": "diagnosis_acute_mesenteric_ischemia",
      "type": "supports",
      "weight": 0.75,
      "evidence": "гипотензия (АД <90 мм рт. ст.)",
      "properties": {}
    },
    {
      "source": "symptom_gipotrofuzia",
      "target": "diagnosis_acute_mesenteric_ischemia",
      "type": "supports",
      "weight": 0.75,
      "evidence": "гипоперфузия (олигоурия, лактацидоз)",
      "properties": {}
    },
    {
      "source": "symptom_peritonit",
      "target": "diagnosis_acute_mesenteric_ischemia",
      "type": "supports",
      "weight": 0.75,
      "evidence": "перитонит",
      "properties": {}
    },
    {
      "source": "symptom_mondora",
      "target": "diagnosis_acute_mesenteric_ischemia",
      "type": "supports",
      "weight": 0.75,
      "evidence": "симптом Мондора – пальпация инфильтрата",
      "properties": {}
    },
    {
      "source": "symptom_vnezapnaya_intensivnaya_abdominalnaya_bol",
      "target": "symptom_spontannoe_oporozhnenie_kishechnika_rvota",
      "type": "co-occurs",
      "weight": 0.95,
      "evidence": "«клиническая триада»: внезапная интенсивная абдоминальная боль, спонтанное опорожнение кишечника (рвота",
      "properties": {}
    },
    {
      "source": "symptom_vnezapnaya_intensivnaya_abdominalnaya_bol",
      "target": "symptom_spontannoe_oporozhnenie_kishechnika_diareya",
      "type": "co-occurs",
      "weight": 0.95,
      "evidence": "«клиническая триада»: внезапная интенсивная абдоминальная боль, спонтанное опорожнение кишечника (диарея",
      "properties": {}
    },
    {
      "source": "symptom_spontannoe_oporozhnenie_kishechnika_rvota",
      "target": "symptom_spontannoe_oporozhnenie_kishechnika_diareya",
      "type": "co-occurs",
      "weight": 0.95,
      "evidence": "спонтанное опорожнение кишечника (рвота и диарея",
      "properties": {}
    },
    {
      "source": "symptom_bradykardia",
      "target": "symptom_simptom_blinova",
      "type": "co-occurs",
      "weight": 0.75,
      "evidence": "возможно повышение артериального давления ... - симптом Блинова, брадикардия",
      "properties": {}
    },
    {
      "source": "symptom_tahikardia",
      "target": "symptom_febrile_or_hypothermia",
      "type": "co-occurs",
      "weight": 0.75,
      "evidence": "тахикардия ... лихорадка",
      "properties": {}
    },
    {
      "source": "symptom_giperkoagulaciya",
      "target": "symptom_povyshennyi_uroven_d_dimera",
      "type": "co-occurs",
      "weight": 0.75,
      "evidence": "гиперкоагуляция; повышенный уровень Д‑димеров",
      "properties": {}
    },
    {
      "source": "symptom_povyshennyi_uroven_lakata",
      "target": "symptom_gipotrofuzia",
      "type": "co-occurs",
      "weight": 0.75,
      "evidence": "повышенный уровень лактата ... гипоперфузия",
      "properties": {}
    }
  ]
}