[
  {
    "source": "nevrologicheskaya_simptomatika",
    "target": "m48_0",
    "type": "supports",
    "weight": 0.5,
    "evidence": "регресс неврологической симптоматики",
    "properties": {}
  },
  {
    "source": "nevrologicheskaya_simptomatika",
    "target": "m51_1",
    "type": "supports",
    "weight": 0.5,
    "evidence": "регресс неврологической симптоматики",
    "properties": {}
  },
  {
    "source": "nevrologicheskaya_simptomatika",
    "target": "m51_0",
    "type": "supports",
    "weight": 0.5,
    "evidence": "регресс неврологической симптоматики",
    "properties": {}
  },
  {
    "source": "nevrologicheskaya_simptomatika",
    "target": "m53_2",
    "type": "supports",
    "weight": 0.5,
    "evidence": "регресс неврологической симптоматики",
    "properties": {}
  },
  {
    "source": "nevrologicheskaya_simptomatika",
    "target": "m43_1",
    "type": "supports",
    "weight": 0.5,
    "evidence": "регресс неврологической симптоматики",
    "properties": {}
  },
  {
    "source": "nevrologicheskaya_simptomatika",
    "target": "s33_0",
    "type": "supports",
    "weight": 0.5,
    "evidence": "регресс неврологической симптоматики",
    "properties": {}
  },
  {
    "source": "nevrologicheskaya_simptomatika",
    "target": "t91_1",
    "type": "supports",
    "weight": 0.5,
    "evidence": "регресс неврологической симптоматики",
    "properties": {}
  },
  {
    "source": "nevrologicheskaya_simptomatika",
    "target": "d16_6",
    "type": "supports",
    "weight": 0.5,
    "evidence": "регресс неврологической симптоматики",
    "properties": {}
  },
  {
    "source": "m48_0",
    "target": "m51_1",
    "type": "appear-with",
    "weight": 0.5,
    "evidence": "• дегенеративные поражения межпозвоночного диска ...; • стеноз позвоночного канала ...",
    "properties": {}
  },
  {
    "source": "m43_1",
    "target": "m53_2",
    "type": "appear-with",
    "weight": 0.5,
    "evidence": "• спондилолистез ...; • ... нестабильность ПДС ...",
    "properties": {}
  },
  {
    "source": "s33_0",
    "target": "t91_1",
    "type": "appear-with",
    "weight": 0.5,
    "evidence": "• травмы и последствия травм ...",
    "properties": {}
  }
]